Ytdl_1080p/__init__.py
Ytdl_1080p/main.py
ytdl_1080p-1.1.0.dist-info/LICENSE
ytdl_1080p-1.1.0.dist-info/METADATA
ytdl_1080p-1.1.0.dist-info/WHEEL
ytdl_1080p-1.1.0.dist-info/entry_points.txt
ytdl_1080p-1.1.0.dist-info/top_level.txt
ytdl_1080p-1.1.0.dist-info/RECORD
